crosseval/__init__.py
crosseval/defaults.py
crosseval/experiment_set.py
crosseval/experiment_set_global_performance.py
crosseval/featurized_data.py
crosseval/metric.py
crosseval/model_global_performance.py
crosseval/model_single_fold_performance.py
crosseval/scores.py
crosseval/train.py
crosseval/utils.py
crosseval/scripts/__init__.py
crosseval/scripts/plot_confusion_matrix.py
crosseval-0.0.5.dist-info/licenses/LICENSE
crosseval-0.0.5.dist-info/METADATA
crosseval-0.0.5.dist-info/WHEEL
crosseval-0.0.5.dist-info/entry_points.txt
crosseval-0.0.5.dist-info/top_level.txt
crosseval-0.0.5.dist-info/RECORD
