Metadata-Version: 2.4
Name: crosseval
Version: 0.0.5
Summary: crosseval
Home-page: https://github.com/maximz/crosseval
Author: Maxim Zaslavsky
Author-email: maxim@maximz.com
License: MIT license
Classifier: Development Status :: 2 - Pre-Alpha
Classifier: Intended Audience :: Developers
Classifier: License :: OSI Approved :: MIT License
Classifier: Natural Language :: English
Classifier: Programming Language :: Python :: 3
Classifier: Programming Language :: Python :: 3.8
Classifier: Programming Language :: Python :: 3.9
Requires-Python: >=3.8
License-File: LICENSE
Requires-Dist: Click>=7.0
Requires-Dist: kdict
Requires-Dist: scikit-learn
Requires-Dist: multiclass-metrics
Requires-Dist: genetools[scanpy]
Requires-Dist: frozendict
Requires-Dist: joblib
Requires-Dist: numpy
Requires-Dist: sentinels
Requires-Dist: enum-mixins
Requires-Dist: pandas
Requires-Dist: typer[all]
Dynamic: author
Dynamic: author-email
Dynamic: classifier
Dynamic: description
Dynamic: description-content-type
Dynamic: home-page
Dynamic: license
Dynamic: license-file
Dynamic: requires-dist
Dynamic: requires-python
Dynamic: summary
